Logges/__init__.py
Logges/cli.py
Logges/logges.py
Logges/utils.py
logges-2.3.dist-info/LICENSE
logges-2.3.dist-info/METADATA
logges-2.3.dist-info/WHEEL
logges-2.3.dist-info/entry_points.txt
logges-2.3.dist-info/RECORD
