Metadata-Version: 2.1
Name: Logges
Version: 2.3
Summary: A simple Logging tool can extract as Markdown, PDF, or print console.
Home-page: https://github.com/uysalserkan/Logges
License: MIT
Keywords: Log,Logging,Logges,Logger,logging,markdown,pdf,console
Author: Serkan UYSAL
Maintainer: Serkan UYSAL
Maintainer-email: uysalserkan08@gmail.com
Requires-Python: >=3.10,<4.0
Classifier: Development Status :: 5 - Production/Stable
Classifier: Intended Audience :: Developers
Classifier: License :: OSI Approved :: MIT License
Classifier: Programming Language :: Python :: 3
Classifier: Programming Language :: Python :: 3.10
Classifier: Programming Language :: Python :: 3.11
Classifier: Programming Language :: Python :: 3.12
Classifier: Programming Language :: Python :: 3.13
Classifier: Programming Language :: Python :: 3 :: Only
Classifier: Programming Language :: Python :: 3.6
Classifier: Programming Language :: Python :: 3.7
Classifier: Programming Language :: Python :: 3.8
Classifier: Programming Language :: Python :: 3.9
Classifier: Topic :: Software Development :: Libraries :: Python Modules
Classifier: Topic :: System :: Logging
Classifier: Topic :: Text Processing :: Markup
Classifier: Topic :: Text Processing :: Markup :: Markdown
Classifier: Topic :: Utilities
Requires-Dist: click (>=8.0.4,<9.0.0)
Requires-Dist: matplotlib (>=3.5.2,<4.0.0)
Requires-Dist: reportlab (>=3.5.67,<4.0.0)
Requires-Dist: rich (>=10.16.2,<11.0.0)
Project-URL: Repository, https://github.com/uysalserkan/Logges
